README.md
setup.py
dokuwiki_fuse/__init__.py
dokuwiki_fuse.egg-info/PKG-INFO
dokuwiki_fuse.egg-info/SOURCES.txt
dokuwiki_fuse.egg-info/dependency_links.txt
dokuwiki_fuse.egg-info/entry_points.txt
dokuwiki_fuse.egg-info/requires.txt
dokuwiki_fuse.egg-info/top_level.txt