Metadata-Version: 2.1
Name: dokuwiki-fuse
Version: 0.0.2
Summary: Fuse for Dokuwiki
Home-page: https://github.com/kindy/fuse-dokuwiki
Author: Kindy Lin
License: UNKNOWN
Platform: UNKNOWN
Classifier: Development Status :: 3 - Alpha
Classifier: License :: OSI Approved :: MIT License
Classifier: Programming Language :: Python :: 2.7
Classifier: Programming Language :: Python :: 3.5
